wds_assbuilder/__init__.py
wds_assbuilder/ass_part.py
wds_assbuilder/create_axis.py
wds_assbuilder/draw.py
wds_assbuilder/events.py
wds_assbuilder/frame.py
wds_assbuilder/match.py
wds_assbuilder/read_ini.py
wds_assbuilder/speaker.py
wds_assbuilder/styles.py
wds_assbuilder-0.1.0.dist-info/LICENSE
wds_assbuilder-0.1.0.dist-info/METADATA
wds_assbuilder-0.1.0.dist-info/WHEEL
wds_assbuilder-0.1.0.dist-info/top_level.txt
wds_assbuilder-0.1.0.dist-info/RECORD
