Metadata-Version: 2.1
Name: wds-assbuilder
Version: 0.1.0
Home-page: https://github.com/DreamGallery/WDS-AssBuilder-Core
Author: DreamGallery
Author-email: infinite.virtual.reality.43@gmail.com
License: MIT
Classifier: Development Status :: 4 - Beta
Classifier: Operating System :: OS Independent
Classifier: License :: OSI Approved :: MIT License
Classifier: Programming Language :: Python :: 3.10
Classifier: Programming Language :: Python :: 3.11
Classifier: Programming Language :: Python :: 3.12
License-File: LICENSE
